golflang_encodings/__init__.py
golflang_encodings/add_encodings.py
golflang_encodings/05AB1E/05ab1e.py
golflang_encodings/05AB1E/__init__.py
golflang_encodings/APL/__init__.py
golflang_encodings/APL/a_plus.py
golflang_encodings/APL/apl_plus.py
golflang_encodings/APL/aplx.py
golflang_encodings/APL/dyalog_apl_classic.py
golflang_encodings/APL/ebcdic_clc_intercal.py
golflang_encodings/Brachylog/__init__.py
golflang_encodings/Brachylog/brachylog.py
golflang_encodings/Charcoal/__init__.py
golflang_encodings/Charcoal/charcoal.py
golflang_encodings/Enlist/__init__.py
golflang_encodings/Enlist/enlist.py
golflang_encodings/Gaia/__init__.py
golflang_encodings/Gaia/gaia.py
golflang_encodings/Husk/__init__.py
golflang_encodings/Husk/husk.py
golflang_encodings/Jelly/__init__.py
golflang_encodings/Jelly/jelly.py
golflang_encodings/Keg/__init__.py
golflang_encodings/Keg/keg.py
golflang_encodings/Ohm/__init__.py
golflang_encodings/Ohm/ohm.py
golflang_encodings/PyOEM/__init__.py
golflang_encodings/PyOEM/pyoem.py
golflang_encodings-1.0.6.dist-info/LICENSE
golflang_encodings-1.0.6.dist-info/METADATA
golflang_encodings-1.0.6.dist-info/WHEEL
golflang_encodings-1.0.6.dist-info/top_level.txt
golflang_encodings-1.0.6.dist-info/RECORD
