Metadata-Version: 2.1
Name: golflang-encodings
Version: 1.0.6
Summary: a bunch of codecs for various esoteric programming languages
Home-page: https://github.com/Axtell/golflang-encodings
Author: Mego
Author-email: UNKNOWN
License: MIT
Keywords: text encoding unicode
Platform: UNKNOWN
Classifier: Development Status :: 5 - Production/Stable
Classifier: License :: OSI Approved :: MIT License
Classifier: Programming Language :: Python :: 3
Classifier: Programming Language :: Python :: 3.3
Classifier: Programming Language :: Python :: 3.4
Classifier: Programming Language :: Python :: 3.5
Classifier: Programming Language :: Python :: 3.6
